tflyrics/__init__.py
tflyrics/constants.py
tflyrics/genius.py
tflyrics/lyrics_ds.py
tflyrics/poet.py
tflyrics-0.2.1.dist-info/LICENSE
tflyrics-0.2.1.dist-info/METADATA
tflyrics-0.2.1.dist-info/WHEEL
tflyrics-0.2.1.dist-info/top_level.txt
tflyrics-0.2.1.dist-info/RECORD
