Metadata-Version: 2.1
Name: tflyrics
Version: 0.2.1
Summary: Generate lyrics with TensorFlow and the Genius API
Home-page: https://github.com/ggiuffre/tf-lyrics
Author: Giorgio Giuffrè
Author-email: giorgiogiuffre23@gmail.com
License: UNKNOWN
Project-URL: Documentation, https://ggiuffre.github.io/tf-lyrics
Project-URL: Source, https://github.com/ggiuffre/tf-lyrics/
Project-URL: Tracker, https://github.com/ggiuffre/tf-lyrics/issues
Keywords: genius tensorflow lyrics scraper tflyrics
Platform: UNKNOWN
Classifier: Development Status :: 3 - Alpha
Classifier: Programming Language :: Python :: 3
Classifier: License :: OSI Approved :: MIT License
Classifier: Operating System :: OS Independent
Classifier: Natural Language :: English
Classifier: Topic :: Scientific/Engineering :: Artificial Intelligence
Classifier: Topic :: Text Processing
Requires-Python: >=3.6
Requires-Dist: beautifulsoup4
Requires-Dist: tensorflow (>=2.0)
